quackamollie/model/llama_index_simple/__init__.py
quackamollie/model/llama_index_simple/model_llama_index_simple.py
quackamollie/model/llama_index_simple/prompt/__init__.py
quackamollie/model/llama_index_simple/prompt/llama_index_simple_prompt.py
quackamollie_model_llama_index_simple-0.1.dist-info/LICENSE
quackamollie_model_llama_index_simple-0.1.dist-info/METADATA
quackamollie_model_llama_index_simple-0.1.dist-info/WHEEL
quackamollie_model_llama_index_simple-0.1.dist-info/entry_points.txt
quackamollie_model_llama_index_simple-0.1.dist-info/top_level.txt
quackamollie_model_llama_index_simple-0.1.dist-info/RECORD
