Metadata-Version: 2.1
Name: quackamollie-model-llama-index-simple
Version: 0.1
Summary: Simple Llama-Index model based on Ollama using Llama-Index model manager for Quackamollie Telegram chat bot
Author-email: QuactorAI <quacktorai@gmail.com>
License: MIT License
Project-URL: Homepage, https://gitlab.com/forge_of_absurd_ducks/quackamollie/lib/models/llama_index/quackamollie_model_llama_index_simple
Keywords: quackamollie,model,llama-index,ollama,telegram,bot,aiogram
Classifier: License :: OSI Approved :: MIT License
Classifier: Programming Language :: Python
Classifier: Programming Language :: Python :: 3 :: Only
Classifier: Programming Language :: Python :: 3.10
Requires-Python: >=3.10
License-File: LICENSE
Requires-Dist: llama-index-llms-ollama
Requires-Dist: quackamollie-core
Requires-Dist: quackamollie-llama-index-model-manager
Provides-Extra: doc
Requires-Dist: sphinx; extra == "doc"
Requires-Dist: sphinx-click; extra == "doc"
Provides-Extra: lint
Requires-Dist: check-manifest; extra == "lint"
Requires-Dist: flake8; extra == "lint"
Requires-Dist: readme-renderer; extra == "lint"
Requires-Dist: safety; extra == "lint"
Requires-Dist: setuptools; extra == "lint"
Requires-Dist: twine; extra == "lint"
Requires-Dist: wheel; extra == "lint"
Provides-Extra: test
Requires-Dist: coverage; extra == "test"
Requires-Dist: pytest; extra == "test"
Requires-Dist: pytest-cov; extra == "test"
Requires-Dist: pytest-xdist; extra == "test"
Requires-Dist: tox; extra == "test"
